comp_2.v
module comp_2 (A,B,L,G,E);
    input [1:0]A,B;
    output L,E,G;
    assign E = (~(A[0]^B[0]))&(~(A[1]^B[1]));
    assign L = (~A[1]&B[1])|((~(A[1]^B[1]))&(~A[0])&B[0]);
    assign G = (A[1]&~B[1])|((~(A[1]^B[1]))&A[0]&(~B[0]));
endmodule

tb_comp.v
module tb_comp;
    reg [1:0]A,B;
    wire L,E,G;

    comp_2 DUT(.A(A), .B(B), .L(L), .E(E), .G(G));
    
    integer i,j;
    initial begin
        $dumpfile("tb_comp.vcd");
        $dumpvars(0,tb_comp);
        for (i=0 ; i<4; i= i+1)
        begin
          for(j=0; j<4; j = j+1 )
          begin
            A = i;
            B = j;
            #10;
          end
        end
        $finish();
    end

endmodule

tb_comp.vcd
$date
	Mon Nov 14 08:22:19 2022
$end
$version
	Icarus Verilog
$end
$timescale
	1s
$end
$scope module tb_comp $end
$var wire 1 ! L $end
$var wire 1 " G $end
$var wire 1 # E $end
$var reg 2 $ A [1:0] $end
$var reg 2 % B [1:0] $end
$var integer 32 & i [31:0] $end
$var integer 32 ' j [31:0] $end
$scope module DUT $end
$var wire 2 ( A [1:0] $end
$var wire 2 ) B [1:0] $end
$var wire 1 # E $end
$var wire 1 " G $end
$var wire 1 ! L $end
$upscope $end
$upscope $end
$enddefinitions $end
$comment Show the parameter values. $end
$dumpall
$end
#0
$dumpvars
b0 )
b0 (
b0 '
b0 &
b0 %
b0 $
1#
0"
0!
$end
#10
0#
1!
b1 %
b1 )
b1 '
#20
b10 %
b10 )
b10 '
#30
b11 %
b11 )
b11 '
#40
1"
0!
b0 %
b0 )
b1 $
b1 (
b1 &
b0 '
#50
1#
0"
b1 %
b1 )
b1 '
#60
0#
0"
1!
b10 %
b10 )
b10 '
#70
b11 %
b11 )
b11 '
#80
1"
0!
b0 %
b0 )
b10 $
b10 (
b10 &
b0 '
#90
b1 %
b1 )
b1 '
#100
1#
0"
b10 %
b10 )
b10 '
#110
0#
1!
b11 %
b11 )
b11 '
#120
1"
0!
b0 %
b0 )
b11 $
b11 (
b11 &
b0 '
#130
b1 %
b1 )
b1 '
#140
1"
b10 %
b10 )
b10 '
#150
1#
0"
b11 %
b11 )
b11 '
#160
b100 &
b100 '
